dmi_scheduler/__init__.py
dmi_scheduler/database.py
dmi_scheduler/database.sql
dmi_scheduler/exceptions.py
dmi_scheduler/job.py
dmi_scheduler/manager.py
dmi_scheduler/queue.py
dmi_scheduler/scheduler.py
dmi_scheduler/worker.py
dmi_scheduler-0.6.0.dist-info/LICENSE
dmi_scheduler-0.6.0.dist-info/METADATA
dmi_scheduler-0.6.0.dist-info/WHEEL
dmi_scheduler-0.6.0.dist-info/top_level.txt
dmi_scheduler-0.6.0.dist-info/RECORD
