Metadata-Version: 2.1
Name: dmi-scheduler
Version: 0.6.0
Summary: A lightweight task scheduler
Home-page: https://github.com/digitalmethodsinitiative/dmi-scheduler
Author: Digital Methods Initiative
Author-email: stijn.peeters@uva.nl
License: UNKNOWN
Platform: UNKNOWN
Classifier: Programming Language :: Python :: 3
Classifier: License :: OSI Approved :: MIT License
Classifier: Operating System :: OS Independent
Requires-Python: >=3.6
